gtax/__init__.py
gtax/gtax_database.py
gtax/gtax_main.py
gtax/sequence.py
gtax/sequence_binning.py
gtax/taxonomy.py
gtax/taxonomy_blast.py
gtax/taxonomy_main.py
gtax/utils.py
gtax-0.0.11.data/data/README.md
gtax-0.0.11.dist-info/LICENSE
gtax-0.0.11.dist-info/METADATA
gtax-0.0.11.dist-info/WHEEL
gtax-0.0.11.dist-info/entry_points.txt
gtax-0.0.11.dist-info/top_level.txt
gtax-0.0.11.dist-info/RECORD
