Metadata-Version: 2.1
Name: gtax
Version: 0.0.11
Summary: Gtax generate a taxonomy sequence database by genomes 
Home-page: https://github.com/ncbi/gtax
Author: Vera Alvarez, Roberto
Author-email: veraalva@ncbi.nlm.nih.gov
Maintainer: Vera Alvarez, Roberto
Maintainer-email: veraalva@ncbi.nlm.nih.gov
License: Public Domain
Project-URL: Documentation, https://gtax.readthedocs.io/
Project-URL: Source, https://github.com/ncbi/gtax
Project-URL: Tracker, https://github.com/ncbi/gtax/issues
Keywords: Biocontainers
Classifier: Development Status :: 3 - Alpha
Classifier: Intended Audience :: Science/Research
Classifier: License :: Public Domain
Classifier: Natural Language :: English
Classifier: Operating System :: Unix
Classifier: Programming Language :: Python :: 3
Classifier: Programming Language :: Python :: 3.8
Classifier: Programming Language :: Python :: 3.9
Classifier: Programming Language :: Python :: 3.10
Classifier: Programming Language :: Python :: 3.11
Classifier: Topic :: Scientific/Engineering :: Bio-Informatics
License-File: LICENSE
Requires-Dist: biopython
Requires-Dist: networkx
Requires-Dist: numpy
Requires-Dist: pandas
Requires-Dist: requests
